{"item":{"id":"66c6080266bbb2aedca6957c","items_in_set":[{"trading_tax":8000,"set_root":true,"icon":"items/unknown.png","thumb":"items/unknown.thumb.png","sub_icon":null,"url_name":"sevagoth_prime","ducats":175,"mastery_level":0,"tags":["prime","warframe","set"],"id":"66c6080266bbb2aedca6957b","en":{"item_name":"Sevagoth Prime Set","description":"The gilded helmsman emerges from the tempest, his shadow a lure for doomed souls.","wiki_link":null,"icon":"items/images/en/sevagoth_prime.56633fb39859f758c11e42519c3521fb.webp","thumb":"items/images/en/thumbs/sevagoth_prime.56633fb39859f758c11e42519c3521fb.128x128.webp","drop":[]},"ru":{"item_name":"Севагот Прайм: Комплект","description":"Позолоченный капитан появляется из бури, а его тень — приманка для обречённых душ.","wiki_link":null,"icon":"items/images/en/sevagoth_prime.56633fb39859f758c11e42519c3521fb.webp","thumb":"items/images/en/thumbs/sevagoth_prime.56633fb39859f758c11e42519c3521fb.128x128.webp","drop":[]},"ko":{"item_name":"세바고스 프라임 세트","description":"금장을 두른 조타수가 폭풍 속에서 나타나, 자신의 그림자를 미끼 삼아 비운의 영혼들을 끌어올립니다.","wiki_link":null,"icon":"items/images/en/sevagoth_prime.56633fb39859f758c11e42519c3521fb.webp","thumb":"items/images/en/thumbs/sevagoth_prime.56633fb39859f758c11e42519c3521fb.128x128.webp","drop":[]},"fr":{"item_name":"Sevagoth Prime - Set","description":"Le timonier doré émerge de la tempête, son ombre étant un appât pour les âmes damnées.","wiki_link":null,"icon":"items/images/en/sevagoth_prime.56633fb39859f758c11e42519c3521fb.webp","thumb":"items/images/en/thumbs/sevagoth_prime.56633fb39859f758c11e42519c3521fb.128x128.webp","drop":[]},"sv":{"item_name":"Sevagoth Prime Set","description":"The gilded helmsman emerges from the tempest, his shadow a lure for doomed souls.","wiki_link":null,"icon":"items/images/en/sevagoth_prime.56633fb39859f758c11e42519c3521fb.webp","thumb":"items/images/en/thumbs/sevagoth_prime.56633fb39859f758c11e42519c3521fb.128x128.webp","drop":[]},"de":{"item_name":"Sevagoth Prime: Set","description":"Der güldene Steuermann taucht aus dem Sturm auf, sein Schatten ein Köder für verdammte Seelen.","wiki_link":null,"icon":"items/images/en/sevagoth_prime.56633fb39859f758c11e42519c3521fb.webp","thumb":"items/images/en/thumbs/sevagoth_prime.56633fb39859f758c11e42519c3521fb.128x128.webp","drop":[]},"zh-hant":{"item_name":"Sevagoth Prime 一套","description":"鍍金的舵手從風暴中出現，他的暗影誘惑那些注定毀滅的亡魂。","wiki_link":null,"icon":"items/images/en/sevagoth_prime.56633fb39859f758c11e42519c3521fb.webp","thumb":"items/images/en/thumbs/sevagoth_prime.56633fb39859f758c11e42519c3521fb.128x128.webp","drop":[]},"zh-hans":{"item_name":"Sevagoth Prime 一套","description":"镀金舵手从暴风雨中现身，他的身影吸引着注定悲怆的灵魂。","wiki_link":null,"icon":"items/images/en/sevagoth_prime.56633fb39859f758c11e42519c3521fb.webp","thumb":"items/images/en/thumbs/sevagoth_prime.56633fb39859f758c11e42519c3521fb.128x128.webp","drop":[]},"pt":{"item_name":"Sevagoth Prime: Conjunto","description":"O comandante dourado emerge da tempestade, com sua sombra atraindo as almas condenadas.","wiki_link":null,"icon":"items/images/en/sevagoth_prime.56633fb39859f758c11e42519c3521fb.webp","thumb":"items/images/en/thumbs/sevagoth_prime.56633fb39859f758c11e42519c3521fb.128x128.webp","drop":[]},"es":{"item_name":"Set de Sevagoth Prime","description":"El timonel dorado emerge de la tempestad y su sombra es un señuelo para las almas condenadas.","wiki_link":null,"icon":"items/images/en/sevagoth_prime.56633fb39859f758c11e42519c3521fb.webp","thumb":"items/images/en/thumbs/sevagoth_prime.56633fb39859f758c11e42519c3521fb.128x128.webp","drop":[]},"pl":{"item_name":"Sevagoth Prime: Zestaw","description":"Pozłacany sternik wyłania się z burzy, a jego cień jest przynętą dla skazanych na zagładę dusz.","wiki_link":null,"icon":"items/images/en/sevagoth_prime.56633fb39859f758c11e42519c3521fb.webp","thumb":"items/images/en/thumbs/sevagoth_prime.56633fb39859f758c11e42519c3521fb.128x128.webp","drop":[]},"cs":{"item_name":"Sevagoth Prime Set","description":"The gilded helmsman emerges from the tempest, his shadow a lure for doomed souls.","wiki_link":null,"icon":"items/images/en/sevagoth_prime.56633fb39859f758c11e42519c3521fb.webp","thumb":"items/images/en/thumbs/sevagoth_prime.56633fb39859f758c11e42519c3521fb.128x128.webp","drop":[]},"uk":{"item_name":"Севаґот-Прайм (комплект)","description":"Позолочений стерновий з’являється з бурі, а тінь його манить приречені душі.","wiki_link":null,"icon":"items/images/en/sevagoth_prime.56633fb39859f758c11e42519c3521fb.webp","thumb":"items/images/en/thumbs/sevagoth_prime.56633fb39859f758c11e42519c3521fb.128x128.webp","drop":[]}},{"trading_tax":2000,"set_root":false,"quantity_for_set":1,"icon":"items/unknown.png","thumb":"items/unknown.thumb.png","sub_icon":"sub_icons/blueprint_128x128.png","url_name":"sevagoth_prime_blueprint","ducats":45,"mastery_level":0,"tags":["prime","warframe","blueprint"],"id":"66c6080266bbb2aedca6957c","en":{"item_name":"Sevagoth Prime Blueprint","description":"The gilded helmsman emerges from the tempest, his shadow a lure for doomed souls.","wiki_link":null,"icon":"items/images/en/sevagoth_prime_blueprint.a81cadf3c1f6e67c92c188534ced77b2.webp","thumb":"items/images/en/thumbs/sevagoth_prime_blueprint.a81cadf3c1f6e67c92c188534ced77b2.128x128.webp","sub_icon":"sub_icons/blueprint_128x128.png","drop":[]},"ru":{"item_name":"Севагот Прайм (Чертеж)","description":"Позолоченный капитан появляется из бури, а его тень — приманка для обречённых душ.","wiki_link":null,"icon":"items/images/en/sevagoth_prime_blueprint.a81cadf3c1f6e67c92c188534ced77b2.webp","thumb":"items/images/en/thumbs/sevagoth_prime_blueprint.a81cadf3c1f6e67c92c188534ced77b2.128x128.webp","sub_icon":"sub_icons/blueprint_128x128.png","drop":[]},"ko":{"item_name":"세바고스 프라임 설계도","description":"금장을 두른 조타수가 폭풍 속에서 나타나, 자신의 그림자를 미끼 삼아 비운의 영혼들을 끌어올립니다.","wiki_link":null,"icon":"items/images/en/sevagoth_prime_blueprint.a81cadf3c1f6e67c92c188534ced77b2.webp","thumb":"items/images/en/thumbs/sevagoth_prime_blueprint.a81cadf3c1f6e67c92c188534ced77b2.128x128.webp","sub_icon":"sub_icons/blueprint_128x128.png","drop":[]},"fr":{"item_name":"Sevagoth Prime (Schéma)","description":"Le timonier doré émerge de la tempête, son ombre étant un appât pour les âmes damnées.","wiki_link":null,"icon":"items/images/en/sevagoth_prime_blueprint.a81cadf3c1f6e67c92c188534ced77b2.webp","thumb":"items/images/en/thumbs/sevagoth_prime_blueprint.a81cadf3c1f6e67c92c188534ced77b2.128x128.webp","sub_icon":"sub_icons/blueprint_128x128.png","drop":[]},"sv":{"item_name":"Sevagoth Prime Blueprint","description":"The gilded helmsman emerges from the tempest, his shadow a lure for doomed souls.","wiki_link":null,"icon":"items/images/en/sevagoth_prime_blueprint.a81cadf3c1f6e67c92c188534ced77b2.webp","thumb":"items/images/en/thumbs/sevagoth_prime_blueprint.a81cadf3c1f6e67c92c188534ced77b2.128x128.webp","sub_icon":"sub_icons/blueprint_128x128.png","drop":[]},"de":{"item_name":"Sevagoth Prime Blaupause","description":"Der güldene Steuermann taucht aus dem Sturm auf, sein Schatten ein Köder für verdammte Seelen.","wiki_link":null,"icon":"items/images/en/sevagoth_prime_blueprint.a81cadf3c1f6e67c92c188534ced77b2.webp","thumb":"items/images/en/thumbs/sevagoth_prime_blueprint.a81cadf3c1f6e67c92c188534ced77b2.128x128.webp","sub_icon":"sub_icons/blueprint_128x128.png","drop":[]},"zh-hant":{"item_name":"Sevagoth Prime 藍圖","description":"鍍金的舵手從風暴中出現，他的暗影誘惑那些注定毀滅的亡魂。","wiki_link":null,"icon":"items/images/en/sevagoth_prime_blueprint.a81cadf3c1f6e67c92c188534ced77b2.webp","thumb":"items/images/en/thumbs/sevagoth_prime_blueprint.a81cadf3c1f6e67c92c188534ced77b2.128x128.webp","sub_icon":"sub_icons/blueprint_128x128.png","drop":[]},"zh-hans":{"item_name":"Sevagoth Prime 蓝图","description":"镀金舵手从暴风雨中现身，他的身影吸引着注定悲怆的灵魂。","wiki_link":null,"icon":"items/images/en/sevagoth_prime_blueprint.a81cadf3c1f6e67c92c188534ced77b2.webp","thumb":"items/images/en/thumbs/sevagoth_prime_blueprint.a81cadf3c1f6e67c92c188534ced77b2.128x128.webp","sub_icon":"sub_icons/blueprint_128x128.png","drop":[]},"pt":{"item_name":"Sevagoth Prime (Diagrama)","description":"O comandante dourado emerge da tempestade, com sua sombra atraindo as almas condenadas.","wiki_link":null,"icon":"items/images/en/sevagoth_prime_blueprint.a81cadf3c1f6e67c92c188534ced77b2.webp","thumb":"items/images/en/thumbs/sevagoth_prime_blueprint.a81cadf3c1f6e67c92c188534ced77b2.128x128.webp","sub_icon":"sub_icons/blueprint_128x128.png","drop":[]},"es":{"item_name":"Plano de Sevagoth Prime","description":"El timonel dorado emerge de la tempestad y su sombra es un señuelo para las almas condenadas.","wiki_link":null,"icon":"items/images/en/sevagoth_prime_blueprint.a81cadf3c1f6e67c92c188534ced77b2.webp","thumb":"items/images/en/thumbs/sevagoth_prime_blueprint.a81cadf3c1f6e67c92c188534ced77b2.128x128.webp","sub_icon":"sub_icons/blueprint_128x128.png","drop":[]},"pl":{"item_name":"Sevagoth Prime - Schemat","description":"Pozłacany sternik wyłania się z burzy, a jego cień jest przynętą dla skazanych na zagładę dusz.","wiki_link":null,"icon":"items/images/en/sevagoth_prime_blueprint.a81cadf3c1f6e67c92c188534ced77b2.webp","thumb":"items/images/en/thumbs/sevagoth_prime_blueprint.a81cadf3c1f6e67c92c188534ced77b2.128x128.webp","sub_icon":"sub_icons/blueprint_128x128.png","drop":[]},"cs":{"item_name":"Sevagoth Prime Blueprint","description":"The gilded helmsman emerges from the tempest, his shadow a lure for doomed souls.","wiki_link":null,"icon":"items/images/en/sevagoth_prime_blueprint.a81cadf3c1f6e67c92c188534ced77b2.webp","thumb":"items/images/en/thumbs/sevagoth_prime_blueprint.a81cadf3c1f6e67c92c188534ced77b2.128x128.webp","sub_icon":"sub_icons/blueprint_128x128.png","drop":[]},"uk":{"item_name":"Севаґот-Прайм (креслення)","description":"Позолочений стерновий з’являється з бурі, а тінь його манить приречені душі.","wiki_link":null,"icon":"items/images/en/sevagoth_prime_blueprint.a81cadf3c1f6e67c92c188534ced77b2.webp","thumb":"items/images/en/thumbs/sevagoth_prime_blueprint.a81cadf3c1f6e67c92c188534ced77b2.128x128.webp","sub_icon":"sub_icons/blueprint_128x128.png","drop":[]}},{"trading_tax":2000,"set_root":false,"quantity_for_set":1,"icon":"items/unknown.png","thumb":"items/unknown.thumb.png","sub_icon":"sub_icons/warframe/prime_helmet_128x128.png","url_name":"sevagoth_prime_neuroptics_blueprint","ducats":15,"mastery_level":0,"tags":["component","prime","warframe","blueprint"],"id":"66c6080366bbb2aedca6957d","en":{"item_name":"Sevagoth Prime Neuroptics Blueprint","description":"Neuroptics component of the Sevagoth Prime Warframe.","wiki_link":null,"icon":"items/images/en/sevagoth_prime_neuroptics_blueprint.a81cadf3c1f6e67c92c188534ced77b2.webp","thumb":"items/images/en/thumbs/sevagoth_prime_neuroptics_blueprint.a81cadf3c1f6e67c92c188534ced77b2.128x128.webp","sub_icon":"sub_icons/warframe/prime_helmet_128x128.png","drop":[]},"ru":{"item_name":"Севагот Прайм: Нейрооптика (Чертеж)","description":"Компонент варфрейма Севагот Прайм: Нейрооптика.","wiki_link":null,"icon":"items/images/en/sevagoth_prime_neuroptics_blueprint.a81cadf3c1f6e67c92c188534ced77b2.webp","thumb":"items/images/en/thumbs/sevagoth_prime_neuroptics_blueprint.a81cadf3c1f6e67c92c188534ced77b2.128x128.webp","sub_icon":"sub_icons/warframe/prime_helmet_128x128.png","drop":[]},"ko":{"item_name":"세바고스 프라임 뉴로옵틱스 설계도","description":"세바고스 프라임 워프레임의 뉴로옵틱스 부분입니다.","wiki_link":null,"icon":"items/images/en/sevagoth_prime_neuroptics_blueprint.a81cadf3c1f6e67c92c188534ced77b2.webp","thumb":"items/images/en/thumbs/sevagoth_prime_neuroptics_blueprint.a81cadf3c1f6e67c92c188534ced77b2.128x128.webp","sub_icon":"sub_icons/warframe/prime_helmet_128x128.png","drop":[]},"fr":{"item_name":"Sevagoth Prime - Neuroptiques (Schéma)","description":"Le composant Neuroptiques de la Warframe Sevagoth Prime.","wiki_link":null,"icon":"items/images/en/sevagoth_prime_neuroptics_blueprint.a81cadf3c1f6e67c92c188534ced77b2.webp","thumb":"items/images/en/thumbs/sevagoth_prime_neuroptics_blueprint.a81cadf3c1f6e67c92c188534ced77b2.128x128.webp","sub_icon":"sub_icons/warframe/prime_helmet_128x128.png","drop":[]},"sv":{"item_name":"Sevagoth Prime Neuroptics Blueprint","description":"Neuroptics component of the Sevagoth Prime Warframe.","wiki_link":null,"icon":"items/images/en/sevagoth_prime_neuroptics_blueprint.a81cadf3c1f6e67c92c188534ced77b2.webp","thumb":"items/images/en/thumbs/sevagoth_prime_neuroptics_blueprint.a81cadf3c1f6e67c92c188534ced77b2.128x128.webp","sub_icon":"sub_icons/warframe/prime_helmet_128x128.png","drop":[]},"de":{"item_name":"Sevagoth Prime: Neuroptik Blaupause","description":"Neuroptik-Komponente für den Sevagoth Prime Warframe.","wiki_link":null,"icon":"items/images/en/sevagoth_prime_neuroptics_blueprint.a81cadf3c1f6e67c92c188534ced77b2.webp","thumb":"items/images/en/thumbs/sevagoth_prime_neuroptics_blueprint.a81cadf3c1f6e67c92c188534ced77b2.128x128.webp","sub_icon":"sub_icons/warframe/prime_helmet_128x128.png","drop":[]},"zh-hant":{"item_name":"Sevagoth Prime 頭部神經光元 藍圖","description":"Sevagoth Prime Warframe 的頭部神經光元組件。","wiki_link":null,"icon":"items/images/en/sevagoth_prime_neuroptics_blueprint.a81cadf3c1f6e67c92c188534ced77b2.webp","thumb":"items/images/en/thumbs/sevagoth_prime_neuroptics_blueprint.a81cadf3c1f6e67c92c188534ced77b2.128x128.webp","sub_icon":"sub_icons/warframe/prime_helmet_128x128.png","drop":[]},"zh-hans":{"item_name":"Sevagoth Prime 头部神经光元 蓝图","description":"Sevagoth Prime 战甲的头部神经光元组件。","wiki_link":null,"icon":"items/images/en/sevagoth_prime_neuroptics_blueprint.a81cadf3c1f6e67c92c188534ced77b2.webp","thumb":"items/images/en/thumbs/sevagoth_prime_neuroptics_blueprint.a81cadf3c1f6e67c92c188534ced77b2.128x128.webp","sub_icon":"sub_icons/warframe/prime_helmet_128x128.png","drop":[]},"pt":{"item_name":"Sevagoth Prime: Neurovisor (Diagrama)","description":"Neurovisor componente do Warframe Sevagoth Prime.","wiki_link":null,"icon":"items/images/en/sevagoth_prime_neuroptics_blueprint.a81cadf3c1f6e67c92c188534ced77b2.webp","thumb":"items/images/en/thumbs/sevagoth_prime_neuroptics_blueprint.a81cadf3c1f6e67c92c188534ced77b2.128x128.webp","sub_icon":"sub_icons/warframe/prime_helmet_128x128.png","drop":[]},"es":{"item_name":"Plano de Neurópticas De Sevagoth Prime","description":"Componente de las neurópticas del warframe Sevagoth Prime.","wiki_link":null,"icon":"items/images/en/sevagoth_prime_neuroptics_blueprint.a81cadf3c1f6e67c92c188534ced77b2.webp","thumb":"items/images/en/thumbs/sevagoth_prime_neuroptics_blueprint.a81cadf3c1f6e67c92c188534ced77b2.128x128.webp","sub_icon":"sub_icons/warframe/prime_helmet_128x128.png","drop":[]},"pl":{"item_name":"Sevagoth Prime: Neurooptyka - Schemat","description":"Neurooptyka dla Warframe'a Sevagoth Prime.","wiki_link":null,"icon":"items/images/en/sevagoth_prime_neuroptics_blueprint.a81cadf3c1f6e67c92c188534ced77b2.webp","thumb":"items/images/en/thumbs/sevagoth_prime_neuroptics_blueprint.a81cadf3c1f6e67c92c188534ced77b2.128x128.webp","sub_icon":"sub_icons/warframe/prime_helmet_128x128.png","drop":[]},"cs":{"item_name":"Sevagoth Prime Neuroptics Blueprint","description":"Neuroptics component of the Sevagoth Prime Warframe.","wiki_link":null,"icon":"items/images/en/sevagoth_prime_neuroptics_blueprint.a81cadf3c1f6e67c92c188534ced77b2.webp","thumb":"items/images/en/thumbs/sevagoth_prime_neuroptics_blueprint.a81cadf3c1f6e67c92c188534ced77b2.128x128.webp","sub_icon":"sub_icons/warframe/prime_helmet_128x128.png","drop":[]},"uk":{"item_name":"Севаґот-Прайм: Нейроптика (креслення)","description":"Деталі нейроптики для ворфрейма Севаґот-прайм.","wiki_link":null,"icon":"items/images/en/sevagoth_prime_neuroptics_blueprint.a81cadf3c1f6e67c92c188534ced77b2.webp","thumb":"items/images/en/thumbs/sevagoth_prime_neuroptics_blueprint.a81cadf3c1f6e67c92c188534ced77b2.128x128.webp","sub_icon":"sub_icons/warframe/prime_helmet_128x128.png","drop":[]}},{"trading_tax":2000,"set_root":false,"quantity_for_set":1,"icon":"items/unknown.png","thumb":"items/unknown.thumb.png","sub_icon":"sub_icons/warframe/prime_chassis_128x128.png","url_name":"sevagoth_prime_chassis_blueprint","ducats":100,"mastery_level":0,"tags":["component","prime","warframe","blueprint"],"id":"66c6080366bbb2aedca6957e","en":{"item_name":"Sevagoth Prime Chassis Blueprint","description":"Chassis component of the Sevagoth Prime Warframe.","wiki_link":null,"icon":"items/images/en/sevagoth_prime_chassis_blueprint.a81cadf3c1f6e67c92c188534ced77b2.webp","thumb":"items/images/en/thumbs/sevagoth_prime_chassis_blueprint.a81cadf3c1f6e67c92c188534ced77b2.128x128.webp","sub_icon":"sub_icons/warframe/prime_chassis_128x128.png","drop":[]},"ru":{"item_name":"Севагот Прайм: Каркас (Чертеж)","description":"Компонент варфрейма Севагот Прайм: Каркас.","wiki_link":null,"icon":"items/images/en/sevagoth_prime_chassis_blueprint.a81cadf3c1f6e67c92c188534ced77b2.webp","thumb":"items/images/en/thumbs/sevagoth_prime_chassis_blueprint.a81cadf3c1f6e67c92c188534ced77b2.128x128.webp","sub_icon":"sub_icons/warframe/prime_chassis_128x128.png","drop":[]},"ko":{"item_name":"세바고스 프라임 섀시 설계도","description":"세바고스 프라임 워프레임의 섀시 부분입니다.","wiki_link":null,"icon":"items/images/en/sevagoth_prime_chassis_blueprint.a81cadf3c1f6e67c92c188534ced77b2.webp","thumb":"items/images/en/thumbs/sevagoth_prime_chassis_blueprint.a81cadf3c1f6e67c92c188534ced77b2.128x128.webp","sub_icon":"sub_icons/warframe/prime_chassis_128x128.png","drop":[]},"fr":{"item_name":"Sevagoth Prime - Châssis (Schéma)","description":"Le composant Châssis de la Warframe Sevagoth Prime.","wiki_link":null,"icon":"items/images/en/sevagoth_prime_chassis_blueprint.a81cadf3c1f6e67c92c188534ced77b2.webp","thumb":"items/images/en/thumbs/sevagoth_prime_chassis_blueprint.a81cadf3c1f6e67c92c188534ced77b2.128x128.webp","sub_icon":"sub_icons/warframe/prime_chassis_128x128.png","drop":[]},"sv":{"item_name":"Sevagoth Prime Chassis Blueprint","description":"Chassis component of the Sevagoth Prime Warframe.","wiki_link":null,"icon":"items/images/en/sevagoth_prime_chassis_blueprint.a81cadf3c1f6e67c92c188534ced77b2.webp","thumb":"items/images/en/thumbs/sevagoth_prime_chassis_blueprint.a81cadf3c1f6e67c92c188534ced77b2.128x128.webp","sub_icon":"sub_icons/warframe/prime_chassis_128x128.png","drop":[]},"de":{"item_name":"Sevagoth Prime: Chassis Blaupause","description":"Chassis-Komponente für den Sevagoth Prime Warframe.","wiki_link":null,"icon":"items/images/en/sevagoth_prime_chassis_blueprint.a81cadf3c1f6e67c92c188534ced77b2.webp","thumb":"items/images/en/thumbs/sevagoth_prime_chassis_blueprint.a81cadf3c1f6e67c92c188534ced77b2.128x128.webp","sub_icon":"sub_icons/warframe/prime_chassis_128x128.png","drop":[]},"zh-hant":{"item_name":"Sevagoth Prime 機體 藍圖","description":"Sevagoth Prime Warframe 的機體組件。","wiki_link":null,"icon":"items/images/en/sevagoth_prime_chassis_blueprint.a81cadf3c1f6e67c92c188534ced77b2.webp","thumb":"items/images/en/thumbs/sevagoth_prime_chassis_blueprint.a81cadf3c1f6e67c92c188534ced77b2.128x128.webp","sub_icon":"sub_icons/warframe/prime_chassis_128x128.png","drop":[]},"zh-hans":{"item_name":"Sevagoth Prime 机体 蓝图","description":"Sevagoth Prime 战甲的机体组件。","wiki_link":null,"icon":"items/images/en/sevagoth_prime_chassis_blueprint.a81cadf3c1f6e67c92c188534ced77b2.webp","thumb":"items/images/en/thumbs/sevagoth_prime_chassis_blueprint.a81cadf3c1f6e67c92c188534ced77b2.128x128.webp","sub_icon":"sub_icons/warframe/prime_chassis_128x128.png","drop":[]},"pt":{"item_name":"Sevagoth Prime: Chassi (Diagrama)","description":"Chassi componente do Warframe Sevagoth Prime.","wiki_link":null,"icon":"items/images/en/sevagoth_prime_chassis_blueprint.a81cadf3c1f6e67c92c188534ced77b2.webp","thumb":"items/images/en/thumbs/sevagoth_prime_chassis_blueprint.a81cadf3c1f6e67c92c188534ced77b2.128x128.webp","sub_icon":"sub_icons/warframe/prime_chassis_128x128.png","drop":[]},"es":{"item_name":"Plano de Chasis De Sevagoth Prime","description":"Componente del chasis del warframe Sevagoth Prime.","wiki_link":null,"icon":"items/images/en/sevagoth_prime_chassis_blueprint.a81cadf3c1f6e67c92c188534ced77b2.webp","thumb":"items/images/en/thumbs/sevagoth_prime_chassis_blueprint.a81cadf3c1f6e67c92c188534ced77b2.128x128.webp","sub_icon":"sub_icons/warframe/prime_chassis_128x128.png","drop":[]},"pl":{"item_name":"Sevagoth Prime: Powłoka - Schemat","description":"Powłoka dla Warframe'a Sevagoth Prime.","wiki_link":null,"icon":"items/images/en/sevagoth_prime_chassis_blueprint.a81cadf3c1f6e67c92c188534ced77b2.webp","thumb":"items/images/en/thumbs/sevagoth_prime_chassis_blueprint.a81cadf3c1f6e67c92c188534ced77b2.128x128.webp","sub_icon":"sub_icons/warframe/prime_chassis_128x128.png","drop":[]},"cs":{"item_name":"Sevagoth Prime Chassis Blueprint","description":"Chassis component of the Sevagoth Prime Warframe.","wiki_link":null,"icon":"items/images/en/sevagoth_prime_chassis_blueprint.a81cadf3c1f6e67c92c188534ced77b2.webp","thumb":"items/images/en/thumbs/sevagoth_prime_chassis_blueprint.a81cadf3c1f6e67c92c188534ced77b2.128x128.webp","sub_icon":"sub_icons/warframe/prime_chassis_128x128.png","drop":[]},"uk":{"item_name":"Севаґот-Прайм: Каркас (креслення)","description":"Деталі каркаса для ворфрейма Севаґота-прайм.","wiki_link":null,"icon":"items/images/en/sevagoth_prime_chassis_blueprint.a81cadf3c1f6e67c92c188534ced77b2.webp","thumb":"items/images/en/thumbs/sevagoth_prime_chassis_blueprint.a81cadf3c1f6e67c92c188534ced77b2.128x128.webp","sub_icon":"sub_icons/warframe/prime_chassis_128x128.png","drop":[]}},{"trading_tax":2000,"set_root":false,"quantity_for_set":1,"icon":"items/unknown.png","thumb":"items/unknown.thumb.png","sub_icon":"sub_icons/warframe/prime_systems_128x128.png","url_name":"sevagoth_prime_systems_blueprint","ducats":15,"mastery_level":0,"tags":["component","prime","warframe","blueprint"],"id":"66c6080366bbb2aedca6957f","en":{"item_name":"Sevagoth Prime Systems Blueprint","description":"Systems component of the Sevagoth Prime Warframe.","wiki_link":null,"icon":"items/images/en/sevagoth_prime_systems_blueprint.a81cadf3c1f6e67c92c188534ced77b2.webp","thumb":"items/images/en/thumbs/sevagoth_prime_systems_blueprint.a81cadf3c1f6e67c92c188534ced77b2.128x128.webp","sub_icon":"sub_icons/warframe/prime_systems_128x128.png","drop":[]},"ru":{"item_name":"Севагот Прайм: Система (Чертеж)","description":"Компонент варфрейма Севагот Прайм: система.","wiki_link":null,"icon":"items/images/en/sevagoth_prime_systems_blueprint.a81cadf3c1f6e67c92c188534ced77b2.webp","thumb":"items/images/en/thumbs/sevagoth_prime_systems_blueprint.a81cadf3c1f6e67c92c188534ced77b2.128x128.webp","sub_icon":"sub_icons/warframe/prime_systems_128x128.png","drop":[]},"ko":{"item_name":"세바고스 프라임 시스템 설계도","description":"세바고스 프라임 워프레임의 시스템 부분입니다.","wiki_link":null,"icon":"items/images/en/sevagoth_prime_systems_blueprint.a81cadf3c1f6e67c92c188534ced77b2.webp","thumb":"items/images/en/thumbs/sevagoth_prime_systems_blueprint.a81cadf3c1f6e67c92c188534ced77b2.128x128.webp","sub_icon":"sub_icons/warframe/prime_systems_128x128.png","drop":[]},"fr":{"item_name":"Sevagoth Prime - Systèmes (Schéma)","description":"Le composant Systèmes de la Warframe Sevagoth Prime.","wiki_link":null,"icon":"items/images/en/sevagoth_prime_systems_blueprint.a81cadf3c1f6e67c92c188534ced77b2.webp","thumb":"items/images/en/thumbs/sevagoth_prime_systems_blueprint.a81cadf3c1f6e67c92c188534ced77b2.128x128.webp","sub_icon":"sub_icons/warframe/prime_systems_128x128.png","drop":[]},"sv":{"item_name":"Sevagoth Prime Systems Blueprint","description":"Systems component of the Sevagoth Prime Warframe.","wiki_link":null,"icon":"items/images/en/sevagoth_prime_systems_blueprint.a81cadf3c1f6e67c92c188534ced77b2.webp","thumb":"items/images/en/thumbs/sevagoth_prime_systems_blueprint.a81cadf3c1f6e67c92c188534ced77b2.128x128.webp","sub_icon":"sub_icons/warframe/prime_systems_128x128.png","drop":[]},"de":{"item_name":"Sevagoth Prime: Systeme Blaupause","description":"Systeme-Komponente für den Sevagoth Prime Warframe.","wiki_link":null,"icon":"items/images/en/sevagoth_prime_systems_blueprint.a81cadf3c1f6e67c92c188534ced77b2.webp","thumb":"items/images/en/thumbs/sevagoth_prime_systems_blueprint.a81cadf3c1f6e67c92c188534ced77b2.128x128.webp","sub_icon":"sub_icons/warframe/prime_systems_128x128.png","drop":[]},"zh-hant":{"item_name":"Sevagoth Prime 系統 藍圖","description":"Sevagoth Prime Warframe 的系統組件。","wiki_link":null,"icon":"items/images/en/sevagoth_prime_systems_blueprint.a81cadf3c1f6e67c92c188534ced77b2.webp","thumb":"items/images/en/thumbs/sevagoth_prime_systems_blueprint.a81cadf3c1f6e67c92c188534ced77b2.128x128.webp","sub_icon":"sub_icons/warframe/prime_systems_128x128.png","drop":[]},"zh-hans":{"item_name":"Sevagoth Prime 系统 蓝图","description":"Sevagoth Prime 战甲的系统组件。","wiki_link":null,"icon":"items/images/en/sevagoth_prime_systems_blueprint.a81cadf3c1f6e67c92c188534ced77b2.webp","thumb":"items/images/en/thumbs/sevagoth_prime_systems_blueprint.a81cadf3c1f6e67c92c188534ced77b2.128x128.webp","sub_icon":"sub_icons/warframe/prime_systems_128x128.png","drop":[]},"pt":{"item_name":"Sevagoth Prime: Sistemas (Diagrama)","description":"Sistemas componentes do Warframe Sevagoth Prime.","wiki_link":null,"icon":"items/images/en/sevagoth_prime_systems_blueprint.a81cadf3c1f6e67c92c188534ced77b2.webp","thumb":"items/images/en/thumbs/sevagoth_prime_systems_blueprint.a81cadf3c1f6e67c92c188534ced77b2.128x128.webp","sub_icon":"sub_icons/warframe/prime_systems_128x128.png","drop":[]},"es":{"item_name":"Plano de Sistemas De Sevagoth Prime","description":"Componente de los sistemas del warframe Sevagoth Prime.","wiki_link":null,"icon":"items/images/en/sevagoth_prime_systems_blueprint.a81cadf3c1f6e67c92c188534ced77b2.webp","thumb":"items/images/en/thumbs/sevagoth_prime_systems_blueprint.a81cadf3c1f6e67c92c188534ced77b2.128x128.webp","sub_icon":"sub_icons/warframe/prime_systems_128x128.png","drop":[]},"pl":{"item_name":"Sevagoth Prime: Systemy - Schemat","description":"Systemy dla Warframe'a Sevagoth Prime.","wiki_link":null,"icon":"items/images/en/sevagoth_prime_systems_blueprint.a81cadf3c1f6e67c92c188534ced77b2.webp","thumb":"items/images/en/thumbs/sevagoth_prime_systems_blueprint.a81cadf3c1f6e67c92c188534ced77b2.128x128.webp","sub_icon":"sub_icons/warframe/prime_systems_128x128.png","drop":[]},"cs":{"item_name":"Sevagoth Prime Systems Blueprint","description":"Systems component of the Sevagoth Prime Warframe.","wiki_link":null,"icon":"items/images/en/sevagoth_prime_systems_blueprint.a81cadf3c1f6e67c92c188534ced77b2.webp","thumb":"items/images/en/thumbs/sevagoth_prime_systems_blueprint.a81cadf3c1f6e67c92c188534ced77b2.128x128.webp","sub_icon":"sub_icons/warframe/prime_systems_128x128.png","drop":[]},"uk":{"item_name":"Севаґот-Прайм: Системи (креслення)","description":"Деталі систем для ворфрейма Севаґота-прайм.","wiki_link":null,"icon":"items/images/en/sevagoth_prime_systems_blueprint.a81cadf3c1f6e67c92c188534ced77b2.webp","thumb":"items/images/en/thumbs/sevagoth_prime_systems_blueprint.a81cadf3c1f6e67c92c188534ced77b2.128x128.webp","sub_icon":"sub_icons/warframe/prime_systems_128x128.png","drop":[]}}]}}